tia_otel_observability_tracer/__init__.py
tia_otel_observability_tracer/tia_otel_observability_tracer.py
tia_otel_observability_tracer-0.1.2.dist-info/METADATA
tia_otel_observability_tracer-0.1.2.dist-info/WHEEL
tia_otel_observability_tracer-0.1.2.dist-info/top_level.txt
tia_otel_observability_tracer-0.1.2.dist-info/RECORD
